.gitignore
MANIFEST.in
README.rst
setup.cfg
setup.py
docs/HISTORY.txt
docs/LICENSE.GPL
docs/LICENSE.txt
docs/MANUAL.txt
raptus/__init__.py
raptus.article.media.egg-info/PKG-INFO
raptus.article.media.egg-info/SOURCES.txt
raptus.article.media.egg-info/dependency_links.txt
raptus.article.media.egg-info/entry_points.txt
raptus.article.media.egg-info/namespace_packages.txt
raptus.article.media.egg-info/not-zip-safe
raptus.article.media.egg-info/requires.txt
raptus.article.media.egg-info/top_level.txt
raptus/article/__init__.py
raptus/article/media/__init__.py
raptus/article/media/adapters.py
raptus/article/media/config.py
raptus/article/media/configure.zcml
raptus/article/media/embedders.py
raptus/article/media/interfaces.py
raptus/article/media/permissions.zcml
raptus/article/media/setuphandlers.py
raptus/article/media/browser/__init__.py
raptus/article/media/browser/audio.gif
raptus/article/media/browser/audio.pt
raptus/article/media/browser/audio.py
raptus/article/media/browser/audio_icon.gif
raptus/article/media/browser/configure.zcml
raptus/article/media/browser/migrations.py
raptus/article/media/browser/migrations.zcml
raptus/article/media/browser/video.gif
raptus/article/media/browser/video.pt
raptus/article/media/browser/video.py
raptus/article/media/browser/video_icon.gif
raptus/article/media/browser/videoembed_icon.gif
raptus/article/media/content/__init__.py
raptus/article/media/content/audio.py
raptus/article/media/content/configure.zcml
raptus/article/media/content/video.py
raptus/article/media/content/videoembed.py
raptus/article/media/i18n/raptus.article-de.mo
raptus/article/media/i18n/raptus.article-de.po
raptus/article/media/i18n/raptus.article-fr.mo
raptus/article/media/i18n/raptus.article-fr.po
raptus/article/media/i18n/raptus.article.pot
raptus/article/media/profiles/default/cssregistry.xml
raptus/article/media/profiles/default/factorytool.xml
raptus/article/media/profiles/default/import_steps.xml
raptus/article/media/profiles/default/metadata.xml
raptus/article/media/profiles/default/propertiestool.xml
raptus/article/media/profiles/default/raptus.article.media_install.txt
raptus/article/media/profiles/default/rolemap.xml
raptus/article/media/profiles/default/skins.xml
raptus/article/media/profiles/default/types.xml
raptus/article/media/profiles/default/viewlets.xml
