Metadata-Version: 1.1
Name: raptus.article.media
Version: 2.0b11
Summary: Provides audio and video support for articles.
Home-page: https://github.com/Raptus/raptus.article.media
Author: Raptus AG
Author-email: dev@raptus.com
License: GPL
Platform: UNKNOWN
Classifier: Programming Language :: Python
Classifier: Topic :: Software Development :: Libraries :: Python Modules
